thread_chunks/__init__.py
thread_chunks/_actor.py
thread_chunks/_checkpoint.py
thread_chunks/_chunker.py
thread_chunks/_chunker.pyi
thread_chunks/_remote_actor.py
thread_chunks/_remote_actor.pyi
thread_chunks/config.py
thread_chunks-1.0.5.dist-info/METADATA
thread_chunks-1.0.5.dist-info/WHEEL
thread_chunks-1.0.5.dist-info/licenses/LICENSE
thread_chunks-1.0.5.dist-info/RECORD
