Metadata-Version: 2.4
Name: thread-chunks
Version: 1.0.5
Summary: A python package for performing memory intensive computations in parallel using chunks and checkpointing.
Project-URL: Homepage, https://github.com/Christopher-K-Long/thread-chunks
Project-URL: Documentation, https://thread-chunks.readthedocs.io/
Project-URL: Issues, https://github.com/Christopher-K-Long/thread-chunks/issues
Project-URL: Changelog, https://github.com/Christopher-K-Long/thread-chunks/blob/main/ChangeLog.md
Author-email: "Christopher_K._Long" <ckl45@cam.ac.uk>
Maintainer-email: "Christopher_K._Long" <ckl45@cam.ac.uk>
License-Expression: Apache-2.0
License-File: LICENSE
Keywords: checkpointing,chunk,chunking,chunks,multithreading,parallel,parallelisation,thread,threading
Classifier: Operating System :: OS Independent
Classifier: Programming Language :: Python :: 3
Requires-Python: >=3.7
